{
	"experience":
	[
		{
			"date": "2021-2022",
			"type": "Ingénieur Logiciel",
			"title": "Capgemini",
			"description": "Aérospatial : Développement du logiciel du segment sol d’une mission satellitaire d’observation de la Terre. Architecture Client/Serveur.",
			"tags":
			[
				{ "name": "Java", "url": "https://www.java.com/en/" },
				{ "name": "Eclipse", "url": "https://eclipseide.org/"},
				{ "name": "WildFly / JBoss", "url": "https://www.wildfly.org/" },
				{ "name": "PostGreSQL", "url": "https://www.postgresql.org/" },
				{ "name": "Hibernate", "url": "https://hibernate.org/" },
				{ "name": "OpenLDAP","url": "https://en.wikipedia.org/wiki/OpenLDAP"}
			],
			"link": "https://www.capgemini.com/",
			"video": "aucune",
			"image": "resources/images/experiences/Capgemini.webp"
		},
		{
			"date": "2022-2024",
			"type": "Ingénieur Logiciel / FullStack",
			"title": "Infotel",
			"description": "Aéronautique : Développement de la suite Orlando, une solution Web et iOS pour la gestion des compagnies aériennes, et développement d’une application web pour la gestion du CNRS.",
			"tags":
			[
				{ "name": "Java", "url": "https://www.java.com/en/" },
				{ "name": "Angular", "url": "https://angular.io/" },
				{ "name": "NodeJS", "url": "https://nodejs.org/en" },
				{ "name": "MongoDB", "url": "https://www.mongodb.com/" },
				{ "name": "PostGreSQL", "url": "https://www.postgresql.org/" },
				{ "name": "Hibernate", "url": "https://hibernate.org/" },
				{ "name": "Scrum", "url": "https://www.scrum.org/" }
			],
			"link": "https://infotel-consulting.co.uk/",
			"video": "aucune",
			"image": "resources/images/experiences/Infotel.webp"
		},
		{
			"date": "2025",
			"type": "Développeur Web",
			"title": "Freelance",
			"description": "Conception, développement et intégration de deux sites web pour un sanctuaire animalier caritatif et une agence de voyage à Perth, Australie.",
			"tags":
			[
				{ "name": "Wordpress", "url": "https://www.wordpress.com/" },
				{ "name": "Notion", "url": "https://www.notion.com" },
				{ "name": "Figma", "url": "https://www.figma.com" }
			],
			"link": "https://thetravellingsoul.com.au/",
			"video": "aucune",
			"image": "resources/images/experiences/TheTravellingSoul.png"
		}
	]
}